polymorphic_tree/__init__.py
polymorphic_tree/managers.py
polymorphic_tree/models.py
polymorphic_tree/admin/__init__.py
polymorphic_tree/admin/childadmin.py
polymorphic_tree/admin/parentadmin.py
polymorphic_tree/locale/es_AR/LC_MESSAGES/django.mo
polymorphic_tree/locale/es_AR/LC_MESSAGES/django.po
polymorphic_tree/locale/nl/LC_MESSAGES/django.mo
polymorphic_tree/locale/nl/LC_MESSAGES/django.po
polymorphic_tree/static/polymorphic_tree/jquery.cookie.js
polymorphic_tree/static/polymorphic_tree/adminlist/arrow-down.gif
polymorphic_tree/static/polymorphic_tree/adminlist/arrow-up.gif
polymorphic_tree/static/polymorphic_tree/adminlist/nav-bg.gif
polymorphic_tree/static/polymorphic_tree/adminlist/nodetree.css
polymorphic_tree/static/polymorphic_tree/adminlist/nodetree_classic.css
polymorphic_tree/static/polymorphic_tree/adminlist/nodetree_flat.css
polymorphic_tree/static/polymorphic_tree/adminlist/nodetree_grappelli.css
polymorphic_tree/static/polymorphic_tree/adminlist/zebra-flat.png
polymorphic_tree/static/polymorphic_tree/adminlist/zebra-grappelli.png
polymorphic_tree/static/polymorphic_tree/adminlist/zebra.png
polymorphic_tree/static/polymorphic_tree/icons/blank.gif
polymorphic_tree/static/polymorphic_tree/icons/page_new.gif
polymorphic_tree/static/polymorphic_tree/icons/world.gif
polymorphic_tree/static/polymorphic_tree/jqtree/LICENSE
polymorphic_tree/static/polymorphic_tree/jqtree/README.rst
polymorphic_tree/static/polymorphic_tree/jqtree/icons.png
polymorphic_tree/static/polymorphic_tree/jqtree/jqtree.css
polymorphic_tree/static/polymorphic_tree/jqtree/tree.jquery.js
polymorphic_tree/static/polymorphic_tree/jqtree/extra/css/documentation.css
polymorphic_tree/static/polymorphic_tree/jqtree/extra/css/gridless.css
polymorphic_tree/static/polymorphic_tree/jqtree/extra/js/jquery-1.7.2.min.js
polymorphic_tree/static/polymorphic_tree/jqtree/extra/js/jquery.lettering.js
polymorphic_tree/static/polymorphic_tree/jqtree/extra/qunit/qunit.css
django_polymorphic_tree-2.1.dist-info/AUTHORS
django_polymorphic_tree-2.1.dist-info/LICENSE.rst
django_polymorphic_tree-2.1.dist-info/METADATA
django_polymorphic_tree-2.1.dist-info/WHEEL
django_polymorphic_tree-2.1.dist-info/top_level.txt
django_polymorphic_tree-2.1.dist-info/RECORD
